odoo/addons/partner_industry_parent/README.rst
odoo/addons/partner_industry_parent/__init__.py
odoo/addons/partner_industry_parent/__manifest__.py
odoo/addons/partner_industry_parent/i18n/partner_industry_parent.pot
odoo/addons/partner_industry_parent/models/__init__.py
odoo/addons/partner_industry_parent/models/res_partner_industry.py
odoo/addons/partner_industry_parent/readme/CONTRIBUTORS.rst
odoo/addons/partner_industry_parent/readme/DESCRIPTION.rst
odoo/addons/partner_industry_parent/static/description/icon.png
odoo/addons/partner_industry_parent/static/description/index.html
odoo/addons/partner_industry_parent/tests/__init__.py
odoo/addons/partner_industry_parent/tests/test_res_partner_industry.py
odoo/addons/partner_industry_parent/views/res_partner_industry.xml
odoo12_addon_partner_industry_parent-12.0.2.0.0.dist-info/METADATA
odoo12_addon_partner_industry_parent-12.0.2.0.0.dist-info/WHEEL
odoo12_addon_partner_industry_parent-12.0.2.0.0.dist-info/top_level.txt
odoo12_addon_partner_industry_parent-12.0.2.0.0.dist-info/RECORD
