Metadata-Version: 2.1
Name: odoo12-addon-partner-industry-parent
Version: 12.0.2.0.0
Summary: This module add a parent relation to the partner industry
Home-page: https://github.com/OCA/partner-contact
Author: ACSONE SA/NV,Odoo Community Association (OCA)
Author-email: support@odoo-community.org
License: AGPL-3
Platform: UNKNOWN
Classifier: Programming Language :: Python
Classifier: Framework :: Odoo
Classifier: License :: OSI Approved :: GNU Affero General Public License v3
Requires-Python: >=3.5
Requires-Dist: odoo (<12.1dev,>=12.0a)
